termgraphics.py
termgraphics-1.1.0.dist-info/LICENSE.txt
termgraphics-1.1.0.dist-info/METADATA
termgraphics-1.1.0.dist-info/WHEEL
termgraphics-1.1.0.dist-info/top_level.txt
termgraphics-1.1.0.dist-info/RECORD
