Metadata-Version: 2.1
Name: termgraphics
Version: 1.1.0
License-File: LICENSE.txt
Requires-Dist: numpy
